cryptik/__init__.py
cryptik/__main__.py
cryptik/main.py
cryptik-3.12.0.dist-info/LICENSE
cryptik-3.12.0.dist-info/METADATA
cryptik-3.12.0.dist-info/WHEEL
cryptik-3.12.0.dist-info/entry_points.txt
cryptik-3.12.0.dist-info/RECORD
