Metadata-Version: 2.3
Name: cryptik
Version: 3.12.0
Summary: cryptocurrency prices on the command line
License: GPL-3.0-only
Keywords: cli,crypto,currency,bitcoin,ticker
Author: drad
Author-email: sa@adercon.com
Maintainer: drad
Maintainer-email: sa@adercon.com
Requires-Python: >=3.11,<4.0
Classifier: License :: OSI Approved :: GNU General Public License v3 (GPLv3)
Classifier: Programming Language :: Python :: 3
Classifier: Programming Language :: Python :: 3.11
Classifier: Programming Language :: Python :: 3.12
Classifier: Programming Language :: Python :: 3.13
Requires-Dist: arrow (>=1.3.0,<2.0.0)
Requires-Dist: click (>=8.1.7,<9.0.0)
Project-URL: Homepage, https://gitlab.com/drad/cryptik
Project-URL: Repository, https://gitlab.com/drad/cryptik
